llm_store/__init__.py
llm_store/gateway.py
llm_store/store/baserowstore.py
llm_store/store/basestore.py
llm_store-0.1.7.dist-info/METADATA
llm_store-0.1.7.dist-info/WHEEL
llm_store-0.1.7.dist-info/RECORD
