Metadata-Version: 2.1
Name: llm_store
Version: 0.1.7
Summary: LLM Gateway Service
Author: shenyubao
Author-email: shenyubao@yucekj.com
Requires-Python: >=3.8,<4.0
Classifier: Programming Language :: Python :: 3
Classifier: Programming Language :: Python :: 3.8
Classifier: Programming Language :: Python :: 3.9
Classifier: Programming Language :: Python :: 3.10
Classifier: Programming Language :: Python :: 3.11
Classifier: Programming Language :: Python :: 3.12
Classifier: Programming Language :: Python :: 3.13
Requires-Dist: baserowsdk (>=0.0.9,<0.0.10)
Requires-Dist: jinja2 (>=3.1.4,<4.0.0)
Requires-Dist: openai (>=1.54.4,<2.0.0)
